sapysol_jupiter_dao/__init__.py
sapysol_jupiter_dao/anchorpy_governor/__init__.py
sapysol_jupiter_dao/anchorpy_governor/accounts/__init__.py
sapysol_jupiter_dao/anchorpy_governor/accounts/governor.py
sapysol_jupiter_dao/anchorpy_governor/accounts/option_proposal_meta.py
sapysol_jupiter_dao/anchorpy_governor/accounts/proposal.py
sapysol_jupiter_dao/anchorpy_governor/accounts/proposal_meta.py
sapysol_jupiter_dao/anchorpy_governor/accounts/vote.py
sapysol_jupiter_dao/anchorpy_governor/errors/__init__.py
sapysol_jupiter_dao/anchorpy_governor/errors/anchor.py
sapysol_jupiter_dao/anchorpy_governor/errors/custom.py
sapysol_jupiter_dao/anchorpy_governor/instructions/__init__.py
sapysol_jupiter_dao/anchorpy_governor/instructions/activate_proposal.py
sapysol_jupiter_dao/anchorpy_governor/instructions/cancel_proposal.py
sapysol_jupiter_dao/anchorpy_governor/instructions/claim_reward.py
sapysol_jupiter_dao/anchorpy_governor/instructions/create_governor.py
sapysol_jupiter_dao/anchorpy_governor/instructions/create_option_proposal_meta.py
sapysol_jupiter_dao/anchorpy_governor/instructions/create_proposal.py
sapysol_jupiter_dao/anchorpy_governor/instructions/create_proposal_meta.py
sapysol_jupiter_dao/anchorpy_governor/instructions/new_vote.py
sapysol_jupiter_dao/anchorpy_governor/instructions/queue_proposal.py
sapysol_jupiter_dao/anchorpy_governor/instructions/set_governance_params.py
sapysol_jupiter_dao/anchorpy_governor/instructions/set_locker.py
sapysol_jupiter_dao/anchorpy_governor/instructions/set_vote.py
sapysol_jupiter_dao/anchorpy_governor/instructions/set_voting_reward.py
sapysol_jupiter_dao/anchorpy_governor/program_id.py
sapysol_jupiter_dao/anchorpy_governor/types/__init__.py
sapysol_jupiter_dao/anchorpy_governor/types/governance_parameters.py
sapysol_jupiter_dao/anchorpy_governor/types/proposal_account_meta.py
sapysol_jupiter_dao/anchorpy_governor/types/proposal_instruction.py
sapysol_jupiter_dao/anchorpy_governor/types/proposal_state.py
sapysol_jupiter_dao-0.2.0.dist-info/LICENSE
sapysol_jupiter_dao-0.2.0.dist-info/METADATA
sapysol_jupiter_dao-0.2.0.dist-info/WHEEL
sapysol_jupiter_dao-0.2.0.dist-info/RECORD
