Metadata-Version: 2.1
Name: sapysol-jupiter-dao
Version: 0.2.0
Summary: sapysol Jupiter LFG DAO Vote implementation
License: MIT
Author: Anton Platonov
Author-email: anton@platonov.io
Requires-Python: >=3.10,<4.0
Classifier: License :: OSI Approved :: MIT License
Classifier: Programming Language :: Python :: 3
Classifier: Programming Language :: Python :: 3.10
Classifier: Programming Language :: Python :: 3.11
Classifier: Programming Language :: Python :: 3.12
Requires-Dist: anchorpy (>=0.20.0,<0.21.0)
Requires-Dist: sapysol (>=0.5.0)
Requires-Dist: solana (>=0.33.0,<0.34.0)
